smtp_proxy/__init__.py
smtp_proxy/smtp_proxy.py
smtp_proxy-0.1.8.dist-info/METADATA
smtp_proxy-0.1.8.dist-info/WHEEL
smtp_proxy-0.1.8.dist-info/entry_points.txt
smtp_proxy-0.1.8.dist-info/licenses/LICENSE
smtp_proxy-0.1.8.dist-info/RECORD
